module/__init__.py
pythonprogrammersamazingandgood-67.41.dist-info/METADATA
pythonprogrammersamazingandgood-67.41.dist-info/WHEEL
pythonprogrammersamazingandgood-67.41.dist-info/top_level.txt
pythonprogrammersamazingandgood-67.41.dist-info/RECORD
