Metadata-Version: 2.1
Name: pythonprogrammersamazingandgood
Version: 67.41
Summary: the best module to ever exist
